Metadata-Version: 1.0
Name: ukbWrapperRepo
Version: 0.2
Summary: UKB Dataset Access Wrapper
Home-page: https://github.com/tighu20/ukbWrapperRepo
Author: Tigmanshu Chaudhary
Author-email: tic48@pitt.edu
License: UNKNOWN
Platform: UNKNOWN
